geonames_tagger/__init__.py
geonames_tagger/cli.py
geonames_tagger/generate.py
geonames_tagger/model.py
geonames_tagger/settings.py
geonames_tagger/tagger.py
geonames_tagger/util.py
geonames_tagger-1.0.1.dist-info/LICENSE
geonames_tagger-1.0.1.dist-info/METADATA
geonames_tagger-1.0.1.dist-info/NOTICE
geonames_tagger-1.0.1.dist-info/WHEEL
geonames_tagger-1.0.1.dist-info/entry_points.txt
geonames_tagger-1.0.1.dist-info/RECORD
