Metadata-Version: 2.3
Name: geonames_tagger
Version: 1.0.1
Summary: followthemoney query dsl and io helpers
License: MIT
Author: OCCRP Data Team
Author-email: data@occrp.org
Requires-Python: >=3.11,<4
Classifier: Intended Audience :: Developers
Classifier: Operating System :: OS Independent
Classifier: Programming Language :: Python
Classifier: Programming Language :: Python :: 3.11
Classifier: Programming Language :: Python :: 3.12
Classifier: Programming Language :: Python :: 3.13
Requires-Dist: ahocorasick-rs (>=0.22.2,<0.23.0)
Requires-Dist: anystore (>=0.4.0,<0.5.0)
Requires-Dist: jellyfish (>=1.2.0,<2.0.0)
Requires-Dist: normality (>=3.0.1,<4.0.0)
Project-URL: Documentation, https://github.com/dataresearchcenter/geonames_tagger
Project-URL: Homepage, https://github.com/dataresearchcenter/geonames_tagger
Project-URL: Issues, https://github.com/dataresearchcenter/geonames_tagger/issues
Project-URL: Repository, https://github.com/dataresearchcenter/geonames_tagger
